_pygim/__init__.py
_pygim/_error_msgs.py
_pygim/_exceptions.py
_pygim/_iterlib.py
_pygim/typing.py
_pygim/_magic/__init__.py
_pygim/_magic/_cached_type.py
_pygim/_magic/_dispatcher.py
_pygim/_magic/_entangled.py
_pygim/_magic/_gimmick.py
_pygim/_magic/_patch.py
_pygim/_magic/_support.py
_pygim/_magic/_traits.py
_pygim/_magic/traits.py
_pygim/_utils/__init__.py
_pygim/_utils/_fileutils.py
_pygim/_utils/_inspect.py
pygim/__init__.py
pygim/__version__.py
pygim/checklib.py
pygim/exceptions.py
pygim/explib.py
pygim/invariant.py
pygim/iterlib.py
pygim/fileio/__init__.py
pygim/fileio/fileops.py
pygim/fileio/pathset.py
pygim/gimmicks/__init__.py
pygim/gimmicks/_abc_copy.py
pygim/gimmicks/abc.py
pygim/gimmicks/entangled.py
pygim/performance/__init__.py
pygim/performance/dispatch.py
pygim/performance/timing_and_profiling.py
pygim/security/__init__.py
pygim/security/shasum.py
pygim/testing/__init__.py
pygim/testing/diff.py
pygim/testing/testing.py
pygim/utils/__init__.py
pygim/utils/attributes.py
pygim_common-0.6.2.dist-info/METADATA
pygim_common-0.6.2.dist-info/WHEEL
pygim_common-0.6.2.dist-info/top_level.txt
pygim_common-0.6.2.dist-info/RECORD
