Metadata-Version: 2.1
Name: pygim-common
Version: 0.6.2
Summary: Common features for pygim
Home-page: UNKNOWN
License: UNKNOWN
Platform: UNKNOWN
Classifier: Development Status :: 4 - Beta
Classifier: Intended Audience :: Developers
Classifier: License :: OSI Approved :: MIT License
Classifier: Programming Language :: Python
Classifier: Programming Language :: Python :: 3
Classifier: Programming Language :: Python :: 3.7
Classifier: Programming Language :: Python :: 3.8
Classifier: Programming Language :: Python :: 3.9
Classifier: Programming Language :: Python :: 3.10
Classifier: Programming Language :: Python :: 3.11
Classifier: Topic :: Software Development :: Libraries :: Python Modules
Classifier: Topic :: Software Development :: Quality Assurance
Classifier: Typing :: Typed
Requires-Dist: click >=8.1.3
Requires-Dist: loguru >=0.6.0
Requires-Dist: coverage >=6.4.4
Requires-Dist: pytest >=7.0.0
Requires-Dist: typing-extensions >=4.2.0
Requires-Dist: tabulate >=0.8.10
